fonts/simfang.ttf
models/__init__.py
models/ppocrv5_server/ppocrv5_dict.txt
models/ppocrv5_server/cls/cls.onnx
onnx_ocr/__init__.py
onnx_ocr/cli.py
onnx_ocr/cls_postprocess.py
onnx_ocr/db_postprocess.py
onnx_ocr/imaug.py
onnx_ocr/logger.py
onnx_ocr/model_loader.py
onnx_ocr/ocr_images_pdfs.py
onnx_ocr/onnx_paddleocr.py
onnx_ocr/operators.py
onnx_ocr/predict_base.py
onnx_ocr/predict_cls.py
onnx_ocr/predict_det.py
onnx_ocr/predict_rec.py
onnx_ocr/predict_system.py
onnx_ocr/rec_postprocess.py
onnx_ocr/utils.py
utils/__init__.py
utils/elapsed.py
utils/logger.py
utils/toml.py
onnx_paddleocr-0.2.4.dist-info/METADATA
onnx_paddleocr-0.2.4.dist-info/WHEEL
onnx_paddleocr-0.2.4.dist-info/entry_points.txt
onnx_paddleocr-0.2.4.dist-info/RECORD
