Metadata-Version: 2.4
Name: onnx-paddleocr
Version: 0.2.4
Summary: ONNX PaddleOCR
Project-URL: Homepage, https://pypi.org/project/onnx-paddleocr
Project-URL: Repository, https://github.com/meme2046/onnx-paddleocr
License: MIT
Classifier: Intended Audience :: Developers
Classifier: License :: OSI Approved :: MIT License
Classifier: Programming Language :: Python :: 3
Requires-Python: >=3.10
Requires-Dist: numpy<2.0.0
Requires-Dist: onnxruntime-gpu==1.18.1
Requires-Dist: opencv-python>=4.11.0.86
Requires-Dist: pdf2image>=1.17.0
Requires-Dist: pillow>=12.0.0
Requires-Dist: pyclipper>=1.3.0.post6
Requires-Dist: pymupdf>=1.26.6
Requires-Dist: shapely>=2.1.2
Requires-Dist: toml>=0.10.2
Requires-Dist: typer>=0.20.0
